render_rcdock/__init__.py
render_rcdock/_auto.py
render_rcdock/definitions.py
render_rcdock/js/index.js
render_rcdock/js/index.js.LICENSE.txt
render_rcdock/utils.py
render_rcdock-0.1.0.dist-info/LICENSE
render_rcdock-0.1.0.dist-info/METADATA
render_rcdock-0.1.0.dist-info/WHEEL
render_rcdock-0.1.0.dist-info/RECORD
