Metadata-Version: 2.1
Name: render-rcdock
Version: 0.1.0
Summary: Render binding for Swiper
Author: fdv1
Author-email: francois@pytek.io
Requires-Python: >=3.8,<4.0
Classifier: Programming Language :: Python :: 3
Classifier: Programming Language :: Python :: 3.8
Classifier: Programming Language :: Python :: 3.9
Classifier: Programming Language :: Python :: 3.10
Classifier: Programming Language :: Python :: 3.11
